marlenv/__init__.py
marlenv/env_builder.py
marlenv/env_pool.py
marlenv/exceptions.py
marlenv/mock_env.py
marlenv/py.typed
marlenv/adapters/__init__.py
marlenv/adapters/gym_adapter.py
marlenv/adapters/pettingzoo_adapter.py
marlenv/adapters/pymarl_adapter.py
marlenv/adapters/smac_adapter.py
marlenv/catalog/__init__.py
marlenv/catalog/deepsea.py
marlenv/models/__init__.py
marlenv/models/env.py
marlenv/models/episode.py
marlenv/models/observation.py
marlenv/models/spaces.py
marlenv/models/state.py
marlenv/models/step.py
marlenv/models/transition.py
marlenv/utils/__init__.py
marlenv/utils/cached_property_collector.py
marlenv/utils/import_placeholders.py
marlenv/utils/schedule.py
marlenv/wrappers/__init__.py
marlenv/wrappers/action_randomizer.py
marlenv/wrappers/agent_id_wrapper.py
marlenv/wrappers/available_actions_mask.py
marlenv/wrappers/available_actions_wrapper.py
marlenv/wrappers/blind_wrapper.py
marlenv/wrappers/centralised.py
marlenv/wrappers/delayed_rewards.py
marlenv/wrappers/last_action_wrapper.py
marlenv/wrappers/paddings.py
marlenv/wrappers/penalty_wrapper.py
marlenv/wrappers/potential_shaping.py
marlenv/wrappers/rlenv_wrapper.py
marlenv/wrappers/time_limit.py
marlenv/wrappers/video_recorder.py
multi_agent_rlenv-3.6.3.dist-info/METADATA
multi_agent_rlenv-3.6.3.dist-info/WHEEL
multi_agent_rlenv-3.6.3.dist-info/licenses/LICENSE
multi_agent_rlenv-3.6.3.dist-info/RECORD
