Metadata-Version: 2.4
Name: multi-agent-rlenv
Version: 3.6.3
Summary: A strongly typed Multi-Agent Reinforcement Learning framework
Project-URL: repository, https://github.com/yamoling/multi-agent-rlenv
Author-email: Yannick Molinghen <yannick.molinghen@ulb.be>
License-File: LICENSE
Classifier: Operating System :: OS Independent
Classifier: Programming Language :: Python :: 3
Requires-Python: <4,>=3.10
Requires-Dist: numpy>=2.0.0
Requires-Dist: opencv-python>=4.0
Requires-Dist: typing-extensions>=4.0
Provides-Extra: all
Requires-Dist: gymnasium>0.29.1; extra == 'all'
Requires-Dist: laser-learning-environment>=2.6.1; extra == 'all'
Requires-Dist: overcooked>=0.1.0; extra == 'all'
Requires-Dist: pettingzoo>=1.20; extra == 'all'
Requires-Dist: pymunk>=6.0; extra == 'all'
Requires-Dist: pysc2; extra == 'all'
Requires-Dist: scipy>=1.10; extra == 'all'
Requires-Dist: smac; extra == 'all'
Requires-Dist: torch>=2.0; extra == 'all'
Provides-Extra: gym
Requires-Dist: gymnasium>=0.29.1; extra == 'gym'
Provides-Extra: lle
Requires-Dist: laser-learning-environment>=2.6.1; extra == 'lle'
Provides-Extra: overcooked
Requires-Dist: overcooked>=0.1.0; extra == 'overcooked'
Provides-Extra: pettingzoo
Requires-Dist: pettingzoo>=1.20; extra == 'pettingzoo'
Requires-Dist: pymunk>=6.0; extra == 'pettingzoo'
Requires-Dist: scipy>=1.10; extra == 'pettingzoo'
Provides-Extra: smac
Requires-Dist: pysc2; extra == 'smac'
Requires-Dist: smac; extra == 'smac'
Provides-Extra: torch
Requires-Dist: torch>=2.0; extra == 'torch'
